dynampy/__init__.py
dynampy-0.0.0.dist-info/METADATA
dynampy-0.0.0.dist-info/WHEEL
dynampy-0.0.0.dist-info/top_level.txt
dynampy-0.0.0.dist-info/RECORD
