Metadata-Version: 2.1
Name: dynampy
Version: 0.0.0
Summary: Dynamically organized Python
Home-page: https://github.com/haochuanwei/dynampy
Author: Harry Wei
Author-email: pepsimixt@gmail.com
License: UNKNOWN
Platform: UNKNOWN
Classifier: Programming Language :: Python :: 3
Classifier: License :: OSI Approved :: MIT License
Classifier: Operating System :: OS Independent
Requires-Python: >=3.6
Requires-Dist: deco (>=0.5.2)
Requires-Dist: wasabi (>=0.4.2)
